sciserialize/coders.py
sciserialize/serializers.py
sciserialize/__init__.py
SciSerialize-0.1.1alpha.dist-info/DESCRIPTION.rst
SciSerialize-0.1.1alpha.dist-info/METADATA
SciSerialize-0.1.1alpha.dist-info/metadata.json
SciSerialize-0.1.1alpha.dist-info/RECORD
SciSerialize-0.1.1alpha.dist-info/top_level.txt
SciSerialize-0.1.1alpha.dist-info/WHEEL
