Metadata-Version: 2.0
Name: SciSerialize
Version: 0.1.1alpha
Summary: Serialize scientific data to JSON or MessagePack.
Home-page: https://github.com/SciSerialize/sciserialize-python
Author: Siegfried Guendert
Author-email: siegfried.guendert@googlemail.com
License: MIT
Keywords: scientific serialize data exchange json msgpack
Platform: UNKNOWN
Classifier: Development Status :: 3 - Alpha
Classifier: Intended Audience :: Science/Research
Classifier: Intended Audience :: Developers
Classifier: License :: OSI Approved :: MIT License
Requires-Dist: numpy
Requires-Dist: msgpack-python
Requires-Dist: python-dateutil
Requires-Dist: pandas
